luxorDB_datareader.py
luxordb_datareader-0.1.8.dist-info/METADATA
luxordb_datareader-0.1.8.dist-info/WHEEL
luxordb_datareader-0.1.8.dist-info/top_level.txt
luxordb_datareader-0.1.8.dist-info/RECORD
