Metadata-Version: 2.4
Name: luxordb-datareader
Version: 0.1.8
Summary: Módulo para consultas e cálculos diversos utilizando dados da LuxorDB
Author-email: Sergio <backoffice@luxor.com.br>
License: Proprietary - All rights reserved
Requires-Python: >=3.8
Requires-Dist: pandas>=1.5.0
Requires-Dist: numpy>=1.24.0
Requires-Dist: scipy
Requires-Dist: pyarrow>=12.0.0
Requires-Dist: azure-storage-blob
Requires-Dist: python-dotenv
Requires-Dist: loguru
